odoo8_addon_donation-8.0.0.1.0-py2.7-nspkg.pth
odoo8_addon_donation-8.0.0.1.0.dist-info/top_level.txt
odoo8_addon_donation-8.0.0.1.0.dist-info/WHEEL
odoo8_addon_donation-8.0.0.1.0.dist-info/RECORD
odoo8_addon_donation-8.0.0.1.0.dist-info/metadata.json
odoo8_addon_donation-8.0.0.1.0.dist-info/DESCRIPTION.rst
odoo8_addon_donation-8.0.0.1.0.dist-info/METADATA
odoo8_addon_donation-8.0.0.1.0.dist-info/namespace_packages.txt
odoo_addons/donation/product.py
odoo_addons/donation/donation_campaign.py
odoo_addons/donation/__openerp__.py
odoo_addons/donation/donation_demo.xml
odoo_addons/donation/donation_view.xml
odoo_addons/donation/users_view.xml
odoo_addons/donation/__init__.py
odoo_addons/donation/product_view.xml
odoo_addons/donation/account_view.xml
odoo_addons/donation/README.rst
odoo_addons/donation/donation_campaign_view.xml
odoo_addons/donation/donation.py
odoo_addons/donation/partner_view.xml
odoo_addons/donation/security/donation_security.xml
odoo_addons/donation/security/ir.model.access.csv
odoo_addons/donation/report/donation_report_view.xml
odoo_addons/donation/report/__init__.py
odoo_addons/donation/report/donation_report.py
odoo_addons/donation/i18n/donation.pot
odoo_addons/donation/i18n/fr.po
odoo_addons/donation/wizard/donation_validate_view.xml
odoo_addons/donation/wizard/__init__.py
odoo_addons/donation/wizard/donation_validate.py
odoo_addons/donation/test/validate.yml
odoo_addons/donation/static/description/icon.png
